_ecos.cp37-win_amd64.pyd
ecos/__init__.py
ecos/ecos.py
ecos/version.py
ecos-2.0.14.dist-info/LICENSE
ecos-2.0.14.dist-info/METADATA
ecos-2.0.14.dist-info/WHEEL
ecos-2.0.14.dist-info/top_level.txt
ecos-2.0.14.dist-info/RECORD
